{
  "graph_edges": [
    [
      0,
      1
    ],
    [
      0,
      3
    ],
    [
      1,
      2
    ],
    [
      2,
      3
    ]
  ],
  "graph_nodes": [
    0,
    1,
    2,
    3
  ],
  "cost_matrix": [
    [
      1,
      100
    ],
    [
      100,
      1
    ],
    [
      1,
      100
    ],
    [
      100,
      1
    ]
  ],
  "n_vertices": 4,
  "n_edges": 4,
  "n_colors": 2,
  "metadata": {
    "instance_type": "cycle_even_small",
    "n_vertices": 4,
    "n_colors": 2,
    "known_optimal_cost": 4.0,
    "cycle_length": 4,
    "chromatic_number": 2,
    "is_bipartite": true,
    "description": "Ciclo par C_4: alternancia perfecta, costo \u00f3ptimo 4",
    "optimal_coloring": {
      "0": 0,
      "1": 1,
      "2": 0,
      "3": 1
    },
    "is_feasible": true
  }
}