{
  "instance": "complete_n15_k15_d1.00_s91",
  "metadata": {
    "instance_type": "complete",
    "n_vertices": 15,
    "n_colors": 15,
    "cost_pattern": "uniform",
    "seed": 91,
    "density": 1.0,
    "is_feasible": true,
    "known_optimal_cost": 162.54932911898604,
    "chromatic_number": 15
  },
  "runs": {
    "brute_force": {
      "skipped": true,
      "feasible": false,
      "cost": Infinity,
      "execution_time": 0.0,
      "operations": 0
    },
    "backtracking": {
      "skipped": true,
      "feasible": false,
      "cost": Infinity,
      "execution_time": 0.0,
      "operations": 0
    },
    "intelligent_backtracking": {
      "skipped": false,
      "feasible": true,
      "cost": 162.54932911898604,
      "execution_time": 8.523890495300293,
      "operations": 568378,
      "solution": {
        "0": 11,
        "1": 14,
        "2": 9,
        "3": 2,
        "4": 4,
        "5": 8,
        "6": 7,
        "7": 3,
        "8": 13,
        "9": 10,
        "10": 0,
        "11": 6,
        "12": 1,
        "13": 5,
        "14": 12
      },
      "optimal": true
    },
    "ilp_solver": {
      "skipped": false,
      "feasible": true,
      "cost": 162.54932911898604,
      "execution_time": 0.5733211040496826,
      "operations": 357750,
      "solution": {
        "0": 11,
        "1": 14,
        "2": 9,
        "3": 2,
        "4": 4,
        "5": 8,
        "6": 7,
        "7": 3,
        "8": 13,
        "9": 10,
        "10": 0,
        "11": 6,
        "12": 1,
        "13": 5,
        "14": 12
      },
      "optimal": true
    },
    "dp_tree": {
      "skipped": true,
      "feasible": false,
      "cost": Infinity,
      "execution_time": 0.0,
      "operations": 0
    },
    "dp_interval": {
      "skipped": false,
      "feasible": true,
      "cost": 273.12936383349717,
      "execution_time": 180.0230896472931,
      "operations": 103357568,
      "solution": {
        "0": 11,
        "1": 13,
        "2": 9,
        "3": 8,
        "4": 4,
        "5": 12,
        "6": 7,
        "7": 3,
        "8": 0,
        "9": 10,
        "10": 1,
        "11": 6,
        "12": 14,
        "13": 5,
        "14": 2
      },
      "optimal": false
    },
    "wsc": {
      "skipped": false,
      "feasible": true,
      "cost": 215.54123712879897,
      "execution_time": 0.002501249313354492,
      "operations": 4486,
      "solution": {
        "14": 12,
        "0": 11,
        "1": 13,
        "2": 9,
        "3": 8,
        "4": 4,
        "5": 14,
        "6": 7,
        "7": 3,
        "8": 0,
        "9": 10,
        "10": 1,
        "11": 6,
        "12": 5,
        "13": 2
      },
      "optimal": false
    },
    "wsc_improved": {
      "skipped": false,
      "feasible": true,
      "cost": 215.54123712879897,
      "execution_time": 0.0004658699035644531,
      "operations": 4937,
      "solution": {
        "14": 12,
        "0": 11,
        "1": 13,
        "2": 9,
        "3": 8,
        "4": 4,
        "5": 14,
        "6": 7,
        "7": 3,
        "8": 0,
        "9": 10,
        "10": 1,
        "11": 6,
        "12": 5,
        "13": 2
      },
      "optimal": false
    },
    "largest_first": {
      "skipped": false,
      "feasible": true,
      "cost": 273.12936383349717,
      "execution_time": 0.009296178817749023,
      "operations": 520,
      "solution": {
        "0": 11,
        "1": 13,
        "2": 9,
        "3": 8,
        "4": 4,
        "5": 12,
        "6": 7,
        "7": 3,
        "8": 0,
        "9": 10,
        "10": 1,
        "11": 6,
        "12": 14,
        "13": 5,
        "14": 2
      },
      "optimal": false
    },
    "dsatur": {
      "skipped": false,
      "feasible": true,
      "cost": 273.12936383349717,
      "execution_time": 0.0016617774963378906,
      "operations": 585,
      "solution": {
        "0": 11,
        "1": 13,
        "2": 9,
        "3": 8,
        "4": 4,
        "5": 12,
        "6": 7,
        "7": 3,
        "8": 0,
        "9": 10,
        "10": 1,
        "11": 6,
        "12": 14,
        "13": 5,
        "14": 2
      },
      "optimal": false
    },
    "rlf": {
      "skipped": false,
      "feasible": true,
      "cost": 213.692651461789,
      "execution_time": 0.004282236099243164,
      "operations": 959,
      "solution": {
        "8": 0,
        "10": 1,
        "1": 2,
        "7": 3,
        "13": 4,
        "3": 5,
        "11": 6,
        "6": 7,
        "5": 8,
        "2": 9,
        "12": 10,
        "0": 11,
        "14": 12,
        "9": 13,
        "4": 14
      },
      "optimal": false
    },
    "peo_greedy": {
      "skipped": false,
      "feasible": true,
      "cost": 273.12936383349717,
      "execution_time": 0.004038810729980469,
      "operations": 1367,
      "solution": {
        "0": 11,
        "1": 13,
        "2": 9,
        "3": 8,
        "4": 4,
        "5": 12,
        "6": 7,
        "7": 3,
        "8": 0,
        "9": 10,
        "10": 1,
        "11": 6,
        "12": 14,
        "13": 5,
        "14": 2
      },
      "optimal": false
    },
    "simulated_annealing": {
      "skipped": false,
      "feasible": true,
      "cost": 268.12964283681185,
      "execution_time": 0.013888120651245117,
      "operations": 405,
      "solution": {
        "0": 11,
        "1": 13,
        "2": 9,
        "3": 12,
        "4": 4,
        "5": 8,
        "6": 7,
        "7": 3,
        "8": 0,
        "9": 10,
        "10": 1,
        "11": 6,
        "12": 14,
        "13": 5,
        "14": 2
      },
      "optimal": false
    },
    "adaptive_sa": {
      "skipped": false,
      "feasible": true,
      "cost": 213.692651461789,
      "execution_time": 0.03402137756347656,
      "operations": 1636,
      "solution": {
        "8": 0,
        "10": 1,
        "1": 2,
        "7": 3,
        "13": 4,
        "3": 5,
        "11": 6,
        "6": 7,
        "5": 8,
        "2": 9,
        "12": 10,
        "0": 11,
        "14": 12,
        "9": 13,
        "4": 14
      },
      "optimal": false
    },
    "trajectory_search": {
      "skipped": false,
      "feasible": true,
      "cost": 215.54123712879897,
      "execution_time": 0.07163810729980469,
      "operations": 101,
      "solution": {
        "14": 12,
        "0": 11,
        "1": 13,
        "2": 9,
        "3": 8,
        "4": 4,
        "5": 14,
        "6": 7,
        "7": 3,
        "8": 0,
        "9": 10,
        "10": 1,
        "11": 6,
        "12": 5,
        "13": 2
      },
      "optimal": false
    },
    "hybrid": {
      "skipped": false,
      "feasible": true,
      "cost": 215.54123712879897,
      "execution_time": 0.07114958763122559,
      "operations": 101,
      "solution": {
        "14": 12,
        "0": 11,
        "1": 13,
        "2": 9,
        "3": 8,
        "4": 4,
        "5": 14,
        "6": 7,
        "7": 3,
        "8": 0,
        "9": 10,
        "10": 1,
        "11": 6,
        "12": 5,
        "13": 2
      },
      "optimal": false
    },
    "adaptive": {
      "skipped": false,
      "feasible": true,
      "cost": 213.692651461789,
      "execution_time": 0.21207809448242188,
      "operations": 1838,
      "solution": {
        "8": 0,
        "10": 1,
        "1": 2,
        "7": 3,
        "13": 4,
        "3": 5,
        "11": 6,
        "6": 7,
        "5": 8,
        "2": 9,
        "12": 10,
        "0": 11,
        "14": 12,
        "9": 13,
        "4": 14
      },
      "optimal": false
    }
  }
}